LICENSE
MANIFEST.in
README.rst
setup.py
leftronicd/__init__.py
leftronicd/constants.py
leftronicd/helpers.py
leftronicd/main.py
leftronicd.egg-info/PKG-INFO
leftronicd.egg-info/SOURCES.txt
leftronicd.egg-info/dependency_links.txt
leftronicd.egg-info/entry_points.txt
leftronicd.egg-info/requires.txt
leftronicd.egg-info/top_level.txt
leftronicd/contrib/__init__.py
leftronicd/contrib/github.py