Metadata-Version: 1.0
Name: leftronicd
Version: 1.0.3
Summary: A twisted based daemon to send metrics to leftronic.com
Home-page: https://github.com/ojii/leftronicd
Author: Jonas Obrist
Author-email: ojiidotch@gmail.com
License: BSD
Platform: OS Independent
